odoo/addons/mail_allow_portal_internal_note/README.rst
odoo/addons/mail_allow_portal_internal_note/__init__.py
odoo/addons/mail_allow_portal_internal_note/__manifest__.py
odoo/addons/mail_allow_portal_internal_note/controllers/__init__.py
odoo/addons/mail_allow_portal_internal_note/controllers/mail.py
odoo/addons/mail_allow_portal_internal_note/i18n/mail_allow_portal_internal_note.pot
odoo/addons/mail_allow_portal_internal_note/models/__init__.py
odoo/addons/mail_allow_portal_internal_note/models/res_users.py
odoo/addons/mail_allow_portal_internal_note/readme/CONFIGURE.rst
odoo/addons/mail_allow_portal_internal_note/readme/CONTRIBUTORS.rst
odoo/addons/mail_allow_portal_internal_note/readme/DESCRIPTION.rst
odoo/addons/mail_allow_portal_internal_note/static/description/icon.png
odoo/addons/mail_allow_portal_internal_note/static/description/index.html
odoo/addons/mail_allow_portal_internal_note/static/src/js/composer.js
odoo/addons/mail_allow_portal_internal_note/static/src/xml/mail_portal_template.xml
odoo/addons/mail_allow_portal_internal_note/views/assets.xml
odoo/addons/mail_allow_portal_internal_note/views/res_users.xml
odoo14_addon_mail_allow_portal_internal_note-14.0.1.0.2.dist-info/METADATA
odoo14_addon_mail_allow_portal_internal_note-14.0.1.0.2.dist-info/WHEEL
odoo14_addon_mail_allow_portal_internal_note-14.0.1.0.2.dist-info/top_level.txt
odoo14_addon_mail_allow_portal_internal_note-14.0.1.0.2.dist-info/RECORD
