Metadata-Version: 2.1
Name: odoo14-addon-mail-allow-portal-internal-note
Version: 14.0.1.0.2
Summary: Portal users can access internal messages related to own or other companies
Home-page: https://github.com/OCA/social
Author: Open Source Integrators, Odoo Community Association (OCA)
Author-email: support@odoo-community.org
License: AGPL-3
Platform: UNKNOWN
Classifier: Programming Language :: Python
Classifier: Framework :: Odoo
Classifier: Framework :: Odoo :: 14.0
Classifier: License :: OSI Approved :: GNU Affero General Public License v3
Classifier: Development Status :: 3 - Alpha
Requires-Python: >=3.6
Requires-Dist: odoo (<14.1dev,>=14.0a)
